Repeated_Test_Framework-0.1.1rc2.dist-info/DESCRIPTION.rst
Repeated_Test_Framework-0.1.1rc2.dist-info/METADATA
Repeated_Test_Framework-0.1.1rc2.dist-info/RECORD
Repeated_Test_Framework-0.1.1rc2.dist-info/WHEEL
Repeated_Test_Framework-0.1.1rc2.dist-info/metadata.json
Repeated_Test_Framework-0.1.1rc2.dist-info/top_level.txt
repeatedtestframework/__init__.py
repeatedtestframework/repeatedtestframework.py
repeatedtestframework/version.py
