Metadata-Version: 2.0
Name: Repeated-Test-Framework
Version: 0.1.1rc2
Summary: Repeated Test Framework: Helper functionality to reduce the amount of boiler plate or repeated code which is implemented when the same functionality is tested multiple times with different data.
Home-page: http://repeatedtestframework.readthedocs.org/en/latest/
Author: Tony Flury
Author-email: anthony.flury@btinternet.com
License: GNU General Public License (GPL)
Keywords: unittest repetition
Platform: UNKNOWN
Classifier: Development Status :: 3 - Alpha
Classifier: Intended Audience :: Developers
Classifier: Topic :: Software Development :: Libraries :: Python Modules
Classifier: License :: OSI Approved :: GNU General Public License (GPL)
Classifier: Programming Language :: Python :: 2.7
Classifier: Programming Language :: Python :: 3.5
Requires-Dist: six
Provides-Extra: dev
Requires-Dist: check-manifest; extra == 'dev'
Provides-Extra: test
Requires-Dist: coverage; extra == 'test'
